{
  "video_id": "5iJM-c_re48",
  "title": "【深夜歌枠】同接50人目指して！🌠初見さん大歓迎歌枠  🎋✨【#vsinger / 七篠さよ】",
  "start_datetime": "2023-01-27T19:32:09Z",
  "thumbnail_url": "https://i.ytimg.com/vi/5iJM-c_re48/maxresdefault.jpg",
  "timestamps": [
    {
      "time": 672,
      "original_time": "11:12",
      "song_id": "Xoe0bvxQcGw",
      "comment_source": "comment",
      "comment_date": "2023-02-01T15:07:27Z"
    },
    {
      "time": 1282,
      "original_time": "21:22",
      "song_id": "OQqxYRF-UVy",
      "comment_source": "comment",
      "comment_date": "2023-02-01T15:07:27Z"
    },
    {
      "time": 1776,
      "original_time": "29:36",
      "song_id": "UUGiGccEeBl",
      "comment_source": "comment",
      "comment_date": "2023-02-01T15:07:27Z"
    },
    {
      "time": 2237,
      "original_time": "37:17",
      "song_id": "rGABXueUigV",
      "comment_source": "comment",
      "comment_date": "2023-02-01T15:07:27Z"
    },
    {
      "time": 2739,
      "original_time": "45:39",
      "song_id": "R9ufr_Jy97N",
      "comment_source": "comment",
      "comment_date": "2023-02-01T15:07:27Z"
    },
    {
      "time": 3336,
      "original_time": "55:36",
      "song_id": "4ybZolUALbZ",
      "comment_source": "comment",
      "comment_date": "2023-02-01T15:07:27Z"
    },
    {
      "time": 3906,
      "original_time": "1:05:06",
      "song_id": "OHBoQwM9fRX",
      "comment_source": "comment",
      "comment_date": "2023-02-01T15:07:27Z"
    },
    {
      "time": 4360,
      "original_time": "1:12:40",
      "song_id": "8KSdbA1fOm7",
      "comment_source": "comment",
      "comment_date": "2023-02-01T15:07:27Z"
    },
    {
      "time": 4893,
      "original_time": "1:21:33",
      "song_id": "xf0sDnJkjAp",
      "comment_source": "comment",
      "comment_date": "2023-02-01T15:07:27Z"
    },
    {
      "time": 5434,
      "original_time": "1:30:34",
      "song_id": "Y6A8BV-FIIP",
      "comment_source": "comment",
      "comment_date": "2023-02-01T15:07:27Z"
    },
    {
      "time": 5933,
      "original_time": "1:38:53",
      "song_id": "zcwUSaSx7fA",
      "comment_source": "comment",
      "comment_date": "2023-02-01T15:07:27Z"
    },
    {
      "time": 6288,
      "original_time": "1:44:48",
      "song_id": "eKzEXGNU1uz",
      "comment_source": "comment",
      "comment_date": "2023-02-01T15:07:27Z"
    },
    {
      "time": 6723,
      "original_time": "1:52:03",
      "song_id": "D5BFDlJ5Lhz",
      "comment_source": "comment",
      "comment_date": "2023-02-01T15:07:27Z"
    },
    {
      "time": 7104,
      "original_time": "1:58:24",
      "song_id": "CGrukB5dlWB",
      "comment_source": "comment",
      "comment_date": "2023-02-01T15:07:27Z"
    },
    {
      "time": 7480,
      "original_time": "2:04:40",
      "song_id": "0c5WvPb9Jsu",
      "comment_source": "comment",
      "comment_date": "2023-02-01T15:07:27Z"
    },
    {
      "time": 7826,
      "original_time": "2:10:26",
      "song_id": "B6poofHY8S_",
      "comment_source": "comment",
      "comment_date": "2023-02-01T15:07:27Z"
    },
    {
      "time": 8327,
      "original_time": "2:18:47",
      "song_id": "l62sn4Qfx0P",
      "comment_source": "comment",
      "comment_date": "2023-02-01T15:07:27Z"
    },
    {
      "time": 8986,
      "original_time": "2:29:46",
      "song_id": "6Jjh81fOkzX",
      "comment_source": "comment",
      "comment_date": "2023-02-01T15:07:27Z"
    }
  ]
}