{
  "video_id": "HZEU5QVbH7E",
  "title": "【 #歌枠 】✧ 雨降りの夜に ✧【雨飼ミヅキ】#エトソラ",
  "start_datetime": "2024-08-31T01:29:02Z",
  "thumbnail_url": "https://i.ytimg.com/vi/HZEU5QVbH7E/maxresdefault.jpg",
  "timestamps": [
    {
      "time": 258,
      "original_time": "00:04:18",
      "song_id": "yvSXRxUHiX4",
      "comment_source": "comment",
      "comment_date": "2024-08-31T02:41:10Z"
    },
    {
      "time": 956,
      "original_time": "00:15:56",
      "song_id": "T9nF-qT4Z6p",
      "comment_source": "comment",
      "comment_date": "2024-08-31T02:41:10Z"
    },
    {
      "time": 1473,
      "original_time": "00:24:33",
      "song_id": "hjtq3AjTxWW",
      "comment_source": "comment",
      "comment_date": "2024-08-31T02:41:10Z"
    },
    {
      "time": 1954,
      "original_time": "00:32:34",
      "song_id": "jvna2lK-_p9",
      "comment_source": "comment",
      "comment_date": "2024-08-31T02:41:10Z"
    },
    {
      "time": 2306,
      "original_time": "00:38:26",
      "song_id": "L3qL-tM5R8s",
      "comment_source": "comment",
      "comment_date": "2024-08-31T02:41:10Z"
    },
    {
      "time": 2894,
      "original_time": "00:48:14",
      "song_id": "5xVmgoKe0xN",
      "comment_source": "comment",
      "comment_date": "2024-08-31T02:41:10Z"
    },
    {
      "time": 3383,
      "original_time": "00:56:23",
      "song_id": "js2aCsQk4FU",
      "comment_source": "comment",
      "comment_date": "2024-08-31T02:41:10Z"
    },
    {
      "time": 3858,
      "original_time": "01:04:18",
      "song_id": "PoFyuC7G3XH",
      "comment_source": "comment",
      "comment_date": "2024-08-31T02:41:10Z"
    }
  ]
}