{
  "video_id": "NFocpAOUfSs",
  "title": "【#初見さん歓迎】久しぶりのアカペラ歌枠やります！！✨【#vtuber / #七篠さよ】#歌枠",
  "start_datetime": "2024-01-27T02:06:43Z",
  "thumbnail_url": "https://i.ytimg.com/vi/NFocpAOUfSs/maxresdefault.jpg",
  "timestamps": [
    {
      "time": 332,
      "original_time": "0:05:32",
      "song_id": "URVqSV4YHub",
      "comment_source": "comment",
      "comment_date": "2024-01-26T14:53:49Z"
    },
    {
      "time": 792,
      "original_time": "0:13:12",
      "song_id": "tgIvyE8DG8P",
      "comment_source": "comment",
      "comment_date": "2024-01-26T14:53:49Z"
    },
    {
      "time": 1534,
      "original_time": "0:25:34",
      "song_id": "flG8_WIEJl5",
      "comment_source": "comment",
      "comment_date": "2024-01-26T14:53:49Z"
    },
    {
      "time": 2136,
      "original_time": "0:35:36",
      "song_id": "Iab6CNzMWuv",
      "comment_source": "comment",
      "comment_date": "2024-01-26T14:53:49Z"
    },
    {
      "time": 2543,
      "original_time": "0:42:23",
      "song_id": "rRbgU0H4B4R",
      "comment_source": "comment",
      "comment_date": "2024-01-26T14:53:49Z"
    },
    {
      "time": 2921,
      "original_time": "0:48:41",
      "song_id": "iRwG0Mdhxp1",
      "comment_source": "comment",
      "comment_date": "2024-01-26T14:53:49Z"
    },
    {
      "time": 3294,
      "original_time": "0:54:54",
      "song_id": "rPKjyixj4oI",
      "comment_source": "comment",
      "comment_date": "2024-01-26T14:53:49Z"
    },
    {
      "time": 3724,
      "original_time": "1:02:04",
      "song_id": "C6LwNtLyTWR",
      "comment_source": "comment",
      "comment_date": "2024-01-26T14:53:49Z"
    },
    {
      "time": 4607,
      "original_time": "1:16:47",
      "song_id": "iBX4onRY_D-",
      "comment_source": "comment",
      "comment_date": "2024-01-26T14:53:49Z"
    }
  ]
}