{
  "video_id": "spIR8Udosls",
  "title": "【#歌枠 】初見さん大歓迎！青空澄み渡る歌枠☀️🫧【＃七篠さよ /＃Vtuber 】#初見さん歓迎",
  "start_datetime": "2025-06-20T15:55:55Z",
  "thumbnail_url": "https://i.ytimg.com/vi/spIR8Udosls/maxresdefault.jpg",
  "timestamps": [
    {
      "time": 712,
      "original_time": "0:11:52",
      "song_id": "NWwQKdm5V1v",
      "comment_source": "comment",
      "comment_date": "2025-06-20T15:07:43Z"
    },
    {
      "time": 1001,
      "original_time": "0:16:41",
      "song_id": "nP2nq0tcXSu",
      "comment_source": "comment",
      "comment_date": "2025-06-20T15:07:43Z"
    },
    {
      "time": 1247,
      "original_time": "0:20:47",
      "song_id": "WGjKMmZ2MoM",
      "comment_source": "comment",
      "comment_date": "2025-06-20T15:07:43Z"
    },
    {
      "time": 1592,
      "original_time": "0:26:32",
      "song_id": "7yPGKuqRmoh",
      "comment_source": "comment",
      "comment_date": "2025-06-20T15:07:43Z"
    },
    {
      "time": 2146,
      "original_time": "0:35:46",
      "song_id": "YStEpY9uIGt",
      "comment_source": "comment",
      "comment_date": "2025-06-20T15:07:43Z"
    },
    {
      "time": 3169,
      "original_time": "0:52:49",
      "song_id": "ZaWV8dZKxMk",
      "comment_source": "comment",
      "comment_date": "2025-06-20T15:07:43Z"
    },
    {
      "time": 3453,
      "original_time": "0:57:33",
      "song_id": "P_-DhpgoHAC",
      "comment_source": "comment",
      "comment_date": "2025-06-20T15:07:43Z"
    },
    {
      "time": 3702,
      "original_time": "1:01:42",
      "song_id": "ZkQ1Uc7cXre",
      "comment_source": "comment",
      "comment_date": "2025-06-20T15:07:43Z"
    },
    {
      "time": 4000,
      "original_time": "1:06:40",
      "song_id": "m0JFMn0taiy",
      "comment_source": "comment",
      "comment_date": "2025-06-20T15:07:43Z"
    },
    {
      "time": 4331,
      "original_time": "1:12:11",
      "song_id": "KIwo066d5p9",
      "comment_source": "comment",
      "comment_date": "2025-06-20T15:07:43Z"
    },
    {
      "time": 4535,
      "original_time": "1:15:35",
      "song_id": "1nsCNGFagKh",
      "comment_source": "comment",
      "comment_date": "2025-06-20T15:07:43Z"
    },
    {
      "time": 4868,
      "original_time": "1:21:08",
      "song_id": "zS5nQni0TMS",
      "comment_source": "comment",
      "comment_date": "2025-06-20T15:07:43Z"
    },
    {
      "time": 5205,
      "original_time": "1:26:45",
      "song_id": "69ZkJKPdbd_",
      "comment_source": "comment",
      "comment_date": "2025-06-20T15:07:43Z"
    },
    {
      "time": 5720,
      "original_time": "1:35:20",
      "song_id": "opKZd-3jKy8",
      "comment_source": "comment",
      "comment_date": "2025-06-20T15:07:43Z"
    },
    {
      "time": 5918,
      "original_time": "1:38:38",
      "song_id": "fwO2llIkcax",
      "comment_source": "comment",
      "comment_date": "2025-06-20T15:07:43Z"
    },
    {
      "time": 6823,
      "original_time": "1:53:43",
      "song_id": "IF-TAesj0xQ",
      "comment_source": "comment",
      "comment_date": "2025-06-20T15:07:43Z"
    },
    {
      "time": 7152,
      "original_time": "1:59:12",
      "song_id": "CHaPoX8JJ1v",
      "comment_source": "comment",
      "comment_date": "2025-06-20T15:07:43Z"
    },
    {
      "time": 7609,
      "original_time": "2:06:49",
      "song_id": "zY-EHv4njXW",
      "comment_source": "comment",
      "comment_date": "2025-06-20T15:07:43Z"
    },
    {
      "time": 7860,
      "original_time": "2:11:00",
      "song_id": "iC6Jn9ban0a",
      "comment_source": "comment",
      "comment_date": "2025-06-20T15:07:43Z"
    },
    {
      "time": 8163,
      "original_time": "2:16:03",
      "song_id": "_KQFBHlprGp",
      "comment_source": "comment",
      "comment_date": "2025-06-20T15:07:43Z"
    },
    {
      "time": 8608,
      "original_time": "2:23:28",
      "song_id": "SKE8WEhseh5",
      "comment_source": "comment",
      "comment_date": "2025-06-20T15:07:43Z"
    },
    {
      "time": 8913,
      "original_time": "2:28:33",
      "song_id": "am27hiNCnO9",
      "comment_source": "comment",
      "comment_date": "2025-06-20T15:07:43Z"
    }
  ]
}