{
  "video_id": "wlGLUvNt8Tg",
  "title": "【#歌枠 】金曜歌枠！！初見さん大歓迎✨リクエストOK🌃【＃七篠さよ /＃Vtuber 】",
  "start_datetime": "2025-04-18T14:50:15Z",
  "thumbnail_url": "https://i.ytimg.com/vi/wlGLUvNt8Tg/maxresdefault.jpg",
  "timestamps": [
    {
      "time": 936,
      "original_time": "0:15:36",
      "song_id": "lrt_DIAGwLn",
      "comment_source": "comment",
      "comment_date": "2025-04-18T14:41:28Z"
    },
    {
      "time": 1301,
      "original_time": "0:21:41",
      "song_id": "J_YX_KJTGdb",
      "comment_source": "comment",
      "comment_date": "2025-04-18T14:41:28Z"
    },
    {
      "time": 1890,
      "original_time": "0:31:30",
      "song_id": "rZgES8QvrFM",
      "comment_source": "comment",
      "comment_date": "2025-04-18T14:41:28Z"
    },
    {
      "time": 2486,
      "original_time": "0:41:26",
      "song_id": "30C6XPrAv0g",
      "comment_source": "comment",
      "comment_date": "2025-04-18T14:41:28Z"
    },
    {
      "time": 2758,
      "original_time": "0:45:58",
      "song_id": "NsCai4NkWqc",
      "comment_source": "comment",
      "comment_date": "2025-04-18T14:41:28Z"
    },
    {
      "time": 3219,
      "original_time": "0:53:39",
      "song_id": "4uGwdfNq-nB",
      "comment_source": "comment",
      "comment_date": "2025-04-18T14:41:28Z"
    },
    {
      "time": 3516,
      "original_time": "0:58:36",
      "song_id": "ekm8QUww049",
      "comment_source": "comment",
      "comment_date": "2025-04-18T14:41:28Z"
    },
    {
      "time": 3849,
      "original_time": "1:04:09",
      "song_id": "YHQ5pJA1cbE",
      "comment_source": "comment",
      "comment_date": "2025-04-18T14:41:28Z"
    },
    {
      "time": 4295,
      "original_time": "1:11:35",
      "song_id": "Bq9MHFWzWad",
      "comment_source": "comment",
      "comment_date": "2025-04-18T14:41:28Z"
    },
    {
      "time": 4552,
      "original_time": "1:15:52",
      "song_id": "hLxj8RrFspo",
      "comment_source": "comment",
      "comment_date": "2025-04-18T14:41:28Z"
    },
    {
      "time": 5206,
      "original_time": "1:26:46",
      "song_id": "b2p2rNoRCFs",
      "comment_source": "comment",
      "comment_date": "2025-04-18T14:41:28Z"
    },
    {
      "time": 5482,
      "original_time": "1:31:22",
      "song_id": "_oh3bQeOWYK",
      "comment_source": "comment",
      "comment_date": "2025-04-18T14:41:28Z"
    },
    {
      "time": 5936,
      "original_time": "1:38:56",
      "song_id": "XceTpwpv4Ym",
      "comment_source": "comment",
      "comment_date": "2025-04-18T14:41:28Z"
    },
    {
      "time": 6147,
      "original_time": "1:42:27",
      "song_id": "O5gM4hdO99z",
      "comment_source": "comment",
      "comment_date": "2025-04-18T14:41:28Z"
    },
    {
      "time": 6919,
      "original_time": "1:55:19",
      "song_id": "JkALr3ygnln",
      "comment_source": "comment",
      "comment_date": "2025-04-18T14:41:28Z"
    },
    {
      "time": 7599,
      "original_time": "2:06:39",
      "song_id": "huMGhFvwD2S",
      "comment_source": "comment",
      "comment_date": "2025-04-18T14:41:28Z"
    },
    {
      "time": 7863,
      "original_time": "2:11:03",
      "song_id": "_H55enpM34A",
      "comment_source": "comment",
      "comment_date": "2025-04-18T14:41:28Z"
    },
    {
      "time": 8210,
      "original_time": "2:16:50",
      "song_id": "s1UdFSJKHT4",
      "comment_source": "comment",
      "comment_date": "2025-04-18T14:41:28Z"
    },
    {
      "time": 9259,
      "original_time": "2:34:19",
      "song_id": "SRMdrFC_WIp",
      "comment_source": "comment",
      "comment_date": "2025-04-18T14:41:28Z"
    }
  ]
}